{
    "A": {
        "100": 4,
        "105": 4,
        "110": 4,
        "115": 4,
        "120": 4,
        "125": 4,
        "130": 4,
        "135": 4,
        "140": 2,
        "145": 4,
        "150": 4,
        "155": 4,
        "160": 4,
        "165": 4,
        "170": 4,
        "175": 4,
        "180": 4,
        "185": 4,
        "190": 4,
        "195": 4,
        "200": 4,
        "205": 4,
        "210": 4,
        "215": 4,
        "220": 4,
        "225": 4,
        "230": 4,
        "235": 4,
        "240": 4,
        "245": 4,
        "250": 4,
        "150": 0,
        "170": 1.0,
        "235": 8,
        "250": 1.0,
        "240": 1.3333333333333333,
        "185": 1.0,
        "135": 1.0,
        "200": 1.0,
        "115": 8,
        "210": 16,
        "110": 0,
        "130": 0,
        "190": 8,
        "195": 1.0,
        "180": 16,
        "105": 8,
        "245": 8,
        "125": 0,
        "120": 1.0,
        "155": 16,
        "160": 8,
        "220": 0,
        "175": 8,
        "140": 0.5,
        "230": 0,
        "225": 1.0,
        "100": 0,
        "165": 0,
        "215": 1.0,
        "145": 16,
        "205": 1.0
    },
    "B": {
        "100": 4,
        "105": 4,
        "110": 4,
        "115": 4,
        "120": 4,
        "125": 4,
        "130": 4,
        "135": 3,
        "140": 2,
        "145": 4,
        "150": 4,
        "155": 4,
        "160": 4,
        "165": 4,
        "170": 4,
        "175": 4,
        "180": 4,
        "185": 4,
        "190": 4,
        "195": 4,
        "200": 4,
        "205": 4,
        "210": 4,
        "215": 4,
        "220": 4,
        "225": 4,
        "230": 4,
        "235": 4,
        "240": 4,
        "245": 4,
        "250": 4,
        "170": 8,
        "175": 16,
        "230": 16,
        "240": 8,
        "200": 1.0,
        "225": 8,
        "120": 1.0,
        "165": 0,
        "245": 8,
        "110": 16,
        "160": 1.0,
        "125": 8,
        "115": 0.5,
        "185": 1.0,
        "235": 8,
        "180": 8,
        "250": 1.0,
        "190": 1.0,
        "100": 1.0,
        "220": 16,
        "140": 0,
        "210": 0,
        "145": 0,
        "105": 8,
        "155": 16,
        "205": 1.0,
        "215": 8,
        "135": 0.75,
        "130": 16,
        "150": 8,
        "195": 0
    },
    "C": {
        "100": 4,
        "105": 4,
        "110": 4,
        "115": 4,
        "120": 4,
        "125": 4,
        "130": 4,
        "135": 4,
        "140": 4,
        "145": 4,
        "150": 4,
        "155": 4,
        "160": 4,
        "165": 4,
        "170": 4,
        "175": 4,
        "180": 4,
        "185": 4,
        "190": 4,
        "195": 4,
        "200": 4,
        "205": 4,
        "210": 4,
        "215": 4,
        "220": 4,
        "225": 4,
        "230": 4,
        "235": 4,
        "240": 4,
        "245": 4,
        "250": 4,
        "170": 0,
        "155": 1.0,
        "190": 8,
        "205": 0,
        "145": 1.0,
        "100": 0,
        "240": 16,
        "210": 1.0,
        "120": 0,
        "105": 1.0,
        "125": 2.0,
        "225": 1.0,
        "245": 8,
        "140": 0,
        "135": 8,
        "110": 16,
        "165": 16,
        "185": 8,
        "115": 16,
        "230": 0,
        "180": 8,
        "250": 0,
        "215": 8,
        "160": 16,
        "235": 1.0,
        "130": 1.0,
        "150": 8,
        "195": 1.0,
        "220": 1.0,
        "175": 8,
        "200": 8
    },
    "P": {
        "100": 4,
        "105": 4,
        "110": 4,
        "115": 4,
        "120": 4,
        "125": 4,
        "130": 4,
        "135": 4,
        "140": 2,
        "145": 4,
        "150": 4,
        "155": 4,
        "160": 4,
        "165": 4,
        "170": 4,
        "175": 4,
        "180": 4,
        "185": 4,
        "190": 4,
        "195": 4,
        "200": 4,
        "205": 4,
        "210": 4,
        "215": 4,
        "220": 4,
        "225": 4,
        "230": 4,
        "235": 4,
        "240": 4,
        "245": 4,
        "250": 4,
        "110": 1.0,
        "160": 8,
        "190": 1.0,
        "230": 8,
        "145": 8,
        "250": 8,
        "165": 1.0,
        "120": 1.0,
        "225": 1.0,
        "115": 8,
        "210": 1.0,
        "215": 1.0,
        "150": 1.0,
        "155": 0,
        "130": 8,
        "105": 0,
        "100": 1.0,
        "235": 0,
        "245": 0,
        "200": 0,
        "240": 8,
        "220": 16,
        "175": 8,
        "185": 1.0,
        "180": 1.0,
        "205": 16,
        "195": 0,
        "135": 8,
        "140": 8,
        "170": 1.0,
        "125": 8
    }
}